setup.py
ailuoge/__init__.py
ailuoge.egg-info/PKG-INFO
ailuoge.egg-info/SOURCES.txt
ailuoge.egg-info/dependency_links.txt
ailuoge.egg-info/top_level.txt