Metadata-Version: 2.1
Name: ailuoge
Version: 1.3.7
Summary: ailuoge
Author: ailuoge
Author-email: 
Keywords: python,ailuoge
Classifier: Development Status :: 1 - Planning
Classifier: Intended Audience :: Developers
Classifier: Programming Language :: Python :: 3
Classifier: Operating System :: Unix
Classifier: Operating System :: MacOS :: MacOS X
Classifier: Operating System :: Microsoft :: Windows
